oshino_admin/__init__.py
oshino_admin/daemon.py
oshino_admin/run.py
oshino_admin/util.py
oshino_admin/version.py
oshino_admin-0.2.0.dist-info/LICENSE
oshino_admin-0.2.0.dist-info/WHEEL
oshino_admin-0.2.0.dist-info/METADATA
oshino_admin-0.2.0.dist-info/RECORD
