Metadata-Version: 2.1
Name: oshino-admin
Version: 0.2.0
Summary: 
Home-page: https://github.com/CodersOfTheNight/oshino-admin
License: MIT
Author: Šarūnas Navickas
Author-email: zaibacu@gmail.com
Requires-Python: >=3.7,<4.0
Classifier: License :: OSI Approved :: MIT License
Classifier: Programming Language :: Python :: 3
Classifier: Programming Language :: Python :: 3.7
Classifier: Programming Language :: Python :: 3.8
Classifier: Programming Language :: Python :: 3.9
Requires-Dist: PyYAML (>=6.0,<7.0)
Requires-Dist: click (>=8.0.3,<9.0.0)
Requires-Dist: daemonize (>=2.5.0,<3.0.0)
Requires-Dist: requests (>=2.27.1,<3.0.0)
Project-URL: Repository, https://github.com/CodersOfTheNight/oshino-admin
